{
  "hash": "3df298d4",
  "configHash": "d09a7247",
  "lockfileHash": "b6671369",
  "browserHash": "343316ae",
  "optimized": {
    "react/jsx-dev-runtime": {
      "src": "../../node_modules/react/jsx-dev-runtime.js",
      "file": "react_jsx-dev-runtime.js",
      "fileHash": "79103abc",
      "needsInterop": true
    },
    "react": {
      "src": "../../node_modules/react/index.js",
      "file": "react.js",
      "fileHash": "5849ddd0",
      "needsInterop": true
    },
    "react-dom/client": {
      "src": "../../node_modules/react-dom/client.js",
      "file": "react-dom_client.js",
      "fileHash": "5a33de33",
      "needsInterop": true
    }
  },
  "chunks": {
    "chunk-Y455YYDO": {
      "file": "chunk-Y455YYDO.js"
    }
  }
}